{
  "type": "Feature",
  "properties": {
    "gn:gn_country":"TV",
    "gn:gn_fcode":"PPL",
    "gn:gn_pop":281,
    "gn:population":281,
    "iso:country":"TV",
    "name:ceb_x_preferred":[
        "Tokelau Village"
    ],
    "name:deu_x_preferred":[
        "Tokelau"
    ],
    "name:eng_x_preferred":[
        "Tokelau"
    ],
    "name:fin_x_preferred":[
        "Tokelau"
    ],
    "name:nld_x_preferred":[
        "Tokelau"
    ],
    "name:pol_x_preferred":[
        "Tokelau"
    ],
    "name:spa_x_preferred":[
        "Tokelau"
    ],
    "qs_pg:aaroncc":"TV",
    "qs_pg:gn_country":"TV",
    "qs_pg:gn_fcode":"PPL",
    "qs_pg:gn_pop":281,
    "qs_pg:name":"Tokelau Village",
    "qs_pg:photos_9r":0,
    "qs_pg:photos_sr":0,
    "qs_pg:pop_sr":2,
    "qs_pg:qs_pg_placetype":"locality",
    "wof:name":"Tokelau Village",
    "wof:placetype":"locality",
    "wof:population":281
},
  "geometry": {"coordinates":[176.31533999999999,-6.28536],"type":"Point"}
}