{
  "type": "Feature",
  "properties": {
    "gn:country":"TV",
    "gn:fcode":"PPL",
    "gn:pop":224,
    "iso:country":"TV",
    "qs:name":"Kulia Village",
    "qs:photos_9r":0,
    "qs:photos_sr":0,
    "qs:pop_sr":"2",
    "wd:wordcount":2478,
    "wof:name":"Kulia Village",
    "wof:placetype":"locality",
    "wof:population":224
},
  "geometry": {"coordinates":[177.33393000000001,-6.10819],"type":"Point"}
}