{
  "type": "Feature",
  "properties": {
    "gn:country":"TV",
    "gn:fcode":"PPL",
    "gn:population":224,
    "iso:country":"TV",
    "name:bel_x_preferred":[
        "\u0412\u043e\u0441\u0442\u0440\u0430\u045e \u041d\u0456\u045e\u0442\u0430\u043e"
    ],
    "name:cat_x_preferred":[
        "Niutao"
    ],
    "name:ceb_x_preferred":[
        "Niutao Island"
    ],
    "name:ces_x_preferred":[
        "Niutao"
    ],
    "name:deu_x_preferred":[
        "Niutao"
    ],
    "name:eng_x_preferred":[
        "Niutao"
    ],
    "name:epo_x_preferred":[
        "Niutao"
    ],
    "name:fao_x_preferred":[
        "Niutao"
    ],
    "name:fas_x_preferred":[
        "\u0646\u06cc\u0648\u062a\u0627\u0626\u0648"
    ],
    "name:fin_x_preferred":[
        "Niutao"
    ],
    "name:fra_x_preferred":[
        "Niutao"
    ],
    "name:glg_x_preferred":[
        "Niutao"
    ],
    "name:hun_x_preferred":[
        "Niutao"
    ],
    "name:ind_x_preferred":[
        "Niutao"
    ],
    "name:ita_x_preferred":[
        "Niutao"
    ],
    "name:jpn_x_preferred":[
        "\u30cb\u30a6\u30bf\u30aa\u5cf6"
    ],
    "name:kat_x_preferred":[
        "\u10dc\u10d8\u10e3\u10e2\u10d0\u10dd"
    ],
    "name:kor_x_preferred":[
        "\ub2c8\uc6b0\ud0c0\uc624\uc12c"
    ],
    "name:lit_x_preferred":[
        "Niutao"
    ],
    "name:mkd_x_preferred":[
        "\u041d\u0438\u0443\u0442\u0430\u043e"
    ],
    "name:nld_x_preferred":[
        "Niutao"
    ],
    "name:nob_x_preferred":[
        "Niutao"
    ],
    "name:pol_x_preferred":[
        "Niutao"
    ],
    "name:por_x_preferred":[
        "Niutao"
    ],
    "name:ron_x_preferred":[
        "Niutao"
    ],
    "name:rus_x_preferred":[
        "\u041d\u0438\u0443\u0442\u0430\u043e"
    ],
    "name:slk_x_preferred":[
        "Niutao"
    ],
    "name:spa_x_preferred":[
        "Niutao"
    ],
    "name:swe_x_preferred":[
        "Niutao"
    ],
    "name:ukr_x_preferred":[
        "\u041d\u0456\u0443\u0442\u0430\u043e"
    ],
    "name:urd_x_preferred":[
        "\u0646\u06cc\u0648\u062a\u0627\u0648"
    ],
    "name:zea_x_preferred":[
        "Niutao"
    ],
    "name:zho_x_preferred":[
        "\u7d10\u9676\u5cf6"
    ],
    "qs:name":"Kulia Village",
    "qs:photos_9r":0,
    "qs:photos_sr":0,
    "qs:pop_sr":"2",
    "wd:wordcount":2478,
    "wof:name":"Kulia Village",
    "wof:placetype":"locality",
    "wof:population":224
},
  "geometry": {"coordinates":[177.33393000000001,-6.10819],"type":"Point"}
}