{
  "type": "Feature",
  "properties": {
    "gn:country":"TV",
    "gn:fcode":"PPL",
    "gn:pop":35,
    "iso:country":"TV",
    "name:bel_x_preferred":[
        "\u0412\u043e\u0441\u0442\u0440\u0430\u045e \u041d\u0456\u045e\u043b\u0430\u043a\u0456\u0442\u0430"
    ],
    "name:cat_x_preferred":[
        "Niulakita"
    ],
    "name:ces_x_preferred":[
        "Niulakita"
    ],
    "name:deu_x_preferred":[
        "Niulakita"
    ],
    "name:eng_x_preferred":[
        "Niulakita"
    ],
    "name:epo_x_preferred":[
        "Niulakita"
    ],
    "name:fao_x_preferred":[
        "Niulakita"
    ],
    "name:fas_x_preferred":[
        "\u0646\u06cc\u0648\u0644\u0627\u06a9\u06cc\u062a\u0627"
    ],
    "name:fin_x_preferred":[
        "Niulakita"
    ],
    "name:fra_x_preferred":[
        "Niulakita"
    ],
    "name:glg_x_preferred":[
        "Niulakita"
    ],
    "name:hun_x_preferred":[
        "Niulakita"
    ],
    "name:ita_x_preferred":[
        "Niulakita"
    ],
    "name:jpn_x_preferred":[
        "\u30cb\u30a6\u30e9\u30ad\u30bf\u5cf6"
    ],
    "name:kat_x_preferred":[
        "\u10dc\u10d8\u10e3\u10da\u10d0\u10d9\u10d8\u10e2\u10d0"
    ],
    "name:kor_x_preferred":[
        "\ub2c8\uc6b8\ub77c\ud0a4\ud0c0 \uc12c"
    ],
    "name:lit_x_preferred":[
        "Niulakita"
    ],
    "name:mkd_x_preferred":[
        "\u041d\u0438\u0443\u043b\u0430\u043a\u0438\u0442\u0430"
    ],
    "name:nld_x_preferred":[
        "Niulakita"
    ],
    "name:nob_x_preferred":[
        "Niulakita"
    ],
    "name:pol_x_preferred":[
        "Niulakita"
    ],
    "name:por_x_preferred":[
        "Niulakita"
    ],
    "name:ron_x_preferred":[
        "Niulakita"
    ],
    "name:rus_x_preferred":[
        "\u041d\u0438\u0443\u043b\u0430\u043a\u0438\u0442\u0430"
    ],
    "name:slk_x_preferred":[
        "Niulakita"
    ],
    "name:spa_x_preferred":[
        "Niulakita"
    ],
    "name:swe_x_preferred":[
        "Niulakita"
    ],
    "name:ukr_x_preferred":[
        "\u041d\u0456\u0443\u043b\u0430\u043a\u0456\u0442\u0430"
    ],
    "name:zho_x_preferred":[
        "\u7d10\u62c9\u57fa\u5854\u5cf6"
    ],
    "qs:name":"Niulakita",
    "qs:photos_9r":0,
    "qs:photos_sr":0,
    "qs:pop_sr":"1",
    "wd:wordcount":955,
    "wof:name":"Niulakita",
    "wof:placetype":"locality",
    "wof:population":35
},
  "geometry": {"coordinates":[179.4667,-10.791],"type":"Point"}
}