{
  "type": "Feature",
  "properties": {
    "gn:country":"TV",
    "gn:fcode":"PPL",
    "gn:population":408,
    "iso:country":"TV",
    "name:ceb_x_preferred":[
        "Tanrake Village"
    ],
    "name:deu_x_preferred":[
        "Tanrake"
    ],
    "name:eng_x_preferred":[
        "Tanrake"
    ],
    "name:fas_x_preferred":[
        "\u062a\u0627\u0646\u0631\u0627\u06a9\u0647"
    ],
    "name:fra_x_preferred":[
        "Tanrake"
    ],
    "name:ita_x_preferred":[
        "Tanrake"
    ],
    "name:mkd_x_preferred":[
        "\u0422\u0430\u043d\u0440\u0430\u043a\u0435"
    ],
    "name:nld_x_preferred":[
        "Tanrake"
    ],
    "name:nob_x_preferred":[
        "Tanrake"
    ],
    "name:pol_x_preferred":[
        "Tanrake"
    ],
    "name:por_x_preferred":[
        "Tanrake"
    ],
    "name:spa_x_preferred":[
        "Tanrake"
    ],
    "name:und_x_variant":[
        "Tapotali"
    ],
    "name:zho_x_preferred":[
        "\u5766\u62c9\u51ef"
    ],
    "qs:name":"Tanrake Village",
    "qs:photos_9r":0,
    "qs:photos_sr":0,
    "qs:pop_sr":"2",
    "wd:wordcount":100,
    "wof:name":"Tanrake Village",
    "wof:placetype":"locality",
    "wof:population":408
},
  "geometry": {"coordinates":[177.14510999999999,-7.24562],"type":"Point"}
}