{
  "type": "Feature",
  "properties": {
    "gn:country":"TV",
    "gn:fcode":"PPL",
    "gn:pop":408,
    "iso:country":"TV",
    "name:dut_x_preferred":[
        "Tanrake"
    ],
    "name:eng_x_preferred":[
        "Tanrake"
    ],
    "name:ger_x_preferred":[
        "Tanrake"
    ],
    "name:mac_x_preferred":[
        "\u0422\u0430\u043d\u0440\u0430\u043a\u0435"
    ],
    "name:nob_x_preferred":[
        "Tanrake"
    ],
    "name:pol_x_preferred":[
        "Tanrake"
    ],
    "name:por_x_preferred":[
        "Tanrake"
    ],
    "name:spa_x_preferred":[
        "Tanrake"
    ],
    "name:unk_x_variant":[
        "Tapotali"
    ],
    "qs:name":"Tanrake Village",
    "qs:photos_9r":0,
    "qs:photos_sr":0,
    "qs:pop_sr":"2",
    "wd:wordcount":100,
    "wof:name":"Tanrake Village",
    "wof:placetype":"locality",
    "wof:population":408
},
  "geometry": {"coordinates":[177.14510999999999,-7.24562],"type":"Point"}
}