{
  "type": "Feature",
  "properties": {
    "gn:country":"TV",
    "gn:fcode":"PPL",
    "gn:pop":308,
    "iso:country":"TV",
    "name:eng_x_preferred":[
        "Tonga"
    ],
    "name:mkd_x_preferred":[
        "\u0422\u043e\u043d\u0433\u0430"
    ],
    "name:nld_x_preferred":[
        "Tonga"
    ],
    "name:nob_x_preferred":[
        "Tonga"
    ],
    "name:pol_x_preferred":[
        "Tonga"
    ],
    "name:spa_x_preferred":[
        "Tonga"
    ],
    "name:unk_x_variant":[
        "Tonga"
    ],
    "qs:name":"Toga Village",
    "qs:photos_9r":0,
    "qs:photos_sr":0,
    "qs:pop_sr":"2",
    "wd:wordcount":194,
    "wof:name":"Toga Village",
    "wof:placetype":"locality",
    "wof:population":308
},
  "geometry": {"coordinates":[176.31471999999999,-6.28764],"type":"Point"}
}