{
  "type": "Feature",
  "properties": {
    "gn:country":"TV",
    "gn:fcode":"PPL",
    "gn:population":308,
    "iso:country":"TV",
    "name:cat_x_preferred":[
        "Tonga"
    ],
    "name:ceb_x_preferred":[
        "Toga Village"
    ],
    "name:eng_x_preferred":[
        "Tonga"
    ],
    "name:fas_x_preferred":[
        "\u062a\u0648\u0646\u06af\u0627"
    ],
    "name:fra_x_preferred":[
        "Toga"
    ],
    "name:mkd_x_preferred":[
        "\u0422\u043e\u043d\u0433\u0430"
    ],
    "name:nld_x_preferred":[
        "Tonga"
    ],
    "name:nob_x_preferred":[
        "Tonga"
    ],
    "name:pol_x_preferred":[
        "Tonga"
    ],
    "name:spa_x_preferred":[
        "Tonga"
    ],
    "name:tur_x_preferred":[
        "Tonga"
    ],
    "name:zho_x_preferred":[
        "\u6e6f\u52a0"
    ],
    "qs:name":"Toga Village",
    "qs:photos_9r":0,
    "qs:photos_sr":0,
    "qs:pop_sr":"2",
    "wd:wordcount":194,
    "wof:name":"Toga Village",
    "wof:placetype":"locality",
    "wof:population":308
},
  "geometry": {"coordinates":[176.31471999999999,-6.28764],"type":"Point"}
}