{
  "type": "Feature",
  "properties": {
    "gn:country":"TV",
    "gn:fcode":"PPL",
    "gn:pop":52,
    "iso:country":"TV",
    "qs:name":"Temotu Village",
    "qs:photos_9r":0,
    "qs:photos_sr":0,
    "qs:pop_sr":"1",
    "wd:wordcount":64,
    "wof:name":"Temotu Village",
    "wof:placetype":"locality",
    "wof:population":52
},
  "geometry": {"coordinates":[178.66748000000001,-7.46168],"type":"Point"}
}