{
  "type": "Feature",
  "properties": {
    "gn:country":"TV",
    "gn:fcode":"PPL",
    "gn:population":219,
    "iso:country":"TV",
    "name:ara_x_preferred":[
        "\u0623\u0633\u0627\u0648"
    ],
    "name:arz_x_preferred":[
        "\u0627\u0633\u0627\u0648"
    ],
    "name:cat_x_preferred":[
        "Asau"
    ],
    "name:ceb_x_preferred":[
        "Asau Village"
    ],
    "name:deu_x_preferred":[
        "Asau"
    ],
    "name:eng_x_preferred":[
        "Asau"
    ],
    "name:fin_x_preferred":[
        "Asau"
    ],
    "name:fra_x_preferred":[
        "Asau"
    ],
    "name:ita_x_preferred":[
        "Asau"
    ],
    "name:lit_x_preferred":[
        "Asau"
    ],
    "name:mkd_x_preferred":[
        "\u0410\u0441\u0430\u0443"
    ],
    "name:nld_x_preferred":[
        "Asau"
    ],
    "name:nob_x_preferred":[
        "Asau"
    ],
    "name:pol_x_preferred":[
        "Asau"
    ],
    "name:spa_x_preferred":[
        "Asau"
    ],
    "name:tur_x_preferred":[
        "Asau"
    ],
    "name:urd_x_preferred":[
        "\u0627\u0633\u0627\u0648"
    ],
    "name:xmf_x_preferred":[
        "\u10d0\u10e1\u10d0\u10e3"
    ],
    "name:zho_x_preferred":[
        "\u963f\u85a9\u70cf"
    ],
    "qs:name":"Asau Village",
    "qs:photos_9r":0,
    "qs:photos_sr":0,
    "qs:pop_sr":"2",
    "wd:wordcount":309,
    "wof:name":"Asau Village",
    "wof:placetype":"locality",
    "wof:population":219
},
  "geometry": {"coordinates":[178.68016,-7.49026],"type":"Point"}
}