{
  "type": "Feature",
  "properties": {
    "gn:country":"TV",
    "gn:fcode":"PPLX",
    "gn:pop":589,
    "iso:country":"TV",
    "qs:name":"Senala Village",
    "qs:photos_9r":0,
    "qs:photos_sr":0,
    "qs:pop_sr":"2",
    "wd:wordcount":36,
    "wof:name":"Senala Village",
    "wof:placetype":"neighbourhood",
    "wof:population":589
},
  "geometry": {"coordinates":[179.19828999999999,-8.5174],"type":"Point"}
}