{
  "type": "Feature",
  "properties": {
    "gn:country":"TV",
    "gn:fcode":"PPLX",
    "gn:pop":589,
    "iso:country":"TV",
    "name:bar_x_preferred":[
        "Gmoana in Tuvalu"
    ],
    "name:ces_x_preferred":[
        "Seznam m\u011bst na Tuvalu"
    ],
    "name:fin_x_preferred":[
        "Luettelo Tuvalun kylist\u00e4"
    ],
    "name:hun_x_preferred":[
        "Tuvalu telep\u00fcl\u00e9sei"
    ],
    "name:kaz_x_preferred":[
        "\u0422\u0443\u0432\u0430\u043b\u0443 \u049b\u0430\u043b\u0430\u043b\u0430\u0440\u044b"
    ],
    "name:pol_x_preferred":[
        "Miejscowo\u015bci Tuvalu"
    ],
    "name:ron_x_preferred":[
        "Lista localit\u0103\u021bilor din Tuvalu"
    ],
    "name:rus_x_preferred":[
        "\u0413\u043e\u0440\u043e\u0434\u0430 \u0422\u0443\u0432\u0430\u043b\u0443"
    ],
    "name:xmf_x_preferred":[
        "\u10e2\u10e3\u10d5\u10d0\u10da\u10e3\u10e8 \u10dc\u10dd\u10e6\u10d4\u10e4\u10d8\u10e8 \u10d4\u10e0\u10d9\u10d4\u10d1\u10e3\u10da\u10d8"
    ],
    "qs:name":"Senala Village",
    "qs:photos_9r":0,
    "qs:photos_sr":0,
    "qs:pop_sr":"2",
    "wd:wordcount":36,
    "wof:name":"Senala Village",
    "wof:placetype":"neighbourhood",
    "wof:population":589
},
  "geometry": {"coordinates":[179.19828999999999,-8.5174],"type":"Point"}
}